{"temperatures":[ {"time": 1752376194992, "temp": 32.8, "bat": -1}, {"time": 1752376820442, "temp": 37.8, "bat": -1}, {"time": 1752377425256, "temp": 39.2, "bat": -1}, {"time": 1752378020074, "temp": 39.7, "bat": -1}, {"time": 1752378619956, "temp": 39.3, "bat": -1}, {"time": 1752379225019, "temp": 39.4, "bat": -1}, {"time": 1752379820685, "temp": 39.4, "bat": -1}, {"time": 1752380419974, "temp": 39.9, "bat": -1}, {"time": 1752381020618, "temp": 39.0, "bat": -1}, {"time": 1752381621878, "temp": 37.5, "bat": -1}, {"time": 1752382222036, "temp": 36.1, "bat": -1}, {"time": 1752382821346, "temp": 35.4, "bat": -1}, {"time": 1752383426320, "temp": 34.3, "bat": -1}, {"time": 1752384021360, "temp": 33.5, "bat": -1}, {"time": 1752384621106, "temp": 32.8, "bat": 3}, {"time": 1752385220490, "temp": 32.2, "bat": 3}, {"time": 1752385821955, "temp": 31.6, "bat": 3}, {"time": 1752386421396, "temp": 31.5, "bat": 3}, {"time": 1752387021642, "temp": 30.0, "bat": 3}, {"time": 1752387621108, "temp": 30.0, "bat": 3}, {"time": 1752388221114, "temp": 31.2, "bat": 3}, {"time": 1752388821237, "temp": 30.0, "bat": 3}, {"time": 1752389425707, "temp": 31.1, "bat": 3} ]}
